Buke_autoTrade_Pypi/Buke_S002_buy_list.py
Buke_autoTrade_Pypi/Buke_S002_sell_list.py
Buke_autoTrade_Pypi/Buke_S004_buy_list.py
Buke_autoTrade_Pypi/Buke_S004_sell_list.py
Buke_autoTrade_Pypi/Buke_S005_buy_list.py
Buke_autoTrade_Pypi/Buke_ST001_buy_list.py
Buke_autoTrade_Pypi/Buke_ST001_sell_list.py
Buke_autoTrade_Pypi/Buke_ST002_buy_list.py
Buke_autoTrade_Pypi/Buke_ST002_sell_list.py
Buke_autoTrade_Pypi/Buke_ST003_buy_list.py
Buke_autoTrade_Pypi/Buke_ST003_sell_list.py
Buke_autoTrade_Pypi/__init__.py
Buke_autoTrade_Pypi/function.py
Buke_autoTrade_Pypi/generate_day_price.py
Buke_autoTrade_Pypi/generate_index_day_price.py
Buke_autoTrade_Pypi/generate_kosdaq_price.py
Buke_autoTrade_Pypi/generate_stock_list.py
Buke_autoTrade_Pypi/generate_trading_days.py
Buke_autoTrade_Pypi/generate_trval_data.py
Buke_autoTrade_Pypi/indicator.py
Buke_autoTrade_Pypi/parameter.py
Buke_autoTrade_Pypi/tools.py
Buke_autoTrade_Pypi-9.1.0.dist-info/METADATA
Buke_autoTrade_Pypi-9.1.0.dist-info/WHEEL
Buke_autoTrade_Pypi-9.1.0.dist-info/top_level.txt
Buke_autoTrade_Pypi-9.1.0.dist-info/RECORD
