Metadata-Version: 2.1
Name: Buke-autoTrade-Pypi
Version: 9.1.0
Summary: test source
Home-page: https://eu4ng.tistory.com
Author: zaza011
Author-email: yesben@naver.com
License: UNKNOWN
Platform: UNKNOWN
Classifier: Programming Language :: Python :: 3
Classifier: License :: OSI Approved :: MIT License
Classifier: Operating System :: OS Independent
Requires-Python: >=3.6
